ipfscluster/__init__.py
ipfscluster/allocations.py
ipfscluster/health.py
ipfscluster/http.py
ipfscluster/peers.py
ipfscluster/pins.py
ipfscluster-0.2.0.dist-info/LICENSE
ipfscluster-0.2.0.dist-info/METADATA
ipfscluster-0.2.0.dist-info/WHEEL
ipfscluster-0.2.0.dist-info/top_level.txt
ipfscluster-0.2.0.dist-info/RECORD
