Metadata-Version: 2.1
Name: ipfscluster
Version: 0.2.0
Summary: HTTP Client for IPFS Cluster.
Home-page: https://gitlab.com/clearos/clearfoundation/py-ipfs-cluster-api
Author: ClearFoundation
Author-email: developer@clearfoundation.com
License: GPL-3.0
Platform: UNKNOWN
Classifier: Development Status :: 2 - Pre-Alpha
Classifier: Intended Audience :: Other Audience
Classifier: Natural Language :: English
Classifier: Operating System :: MacOS
Classifier: Programming Language :: Python :: 3
Classifier: Programming Language :: Python :: 3.7
Requires-Dist: argparse
Requires-Dist: pyparsing
Requires-Dist: termcolor
Requires-Dist: pyyaml
Requires-Dist: requests
Requires-Dist: ipfshttpclient
